LICENSE
README.md
setup.cfg
setup.py
Topsis_Aniket_102003643/102003643.py
Topsis_Aniket_102003643.egg-info/PKG-INFO
Topsis_Aniket_102003643.egg-info/SOURCES.txt
Topsis_Aniket_102003643.egg-info/dependency_links.txt
Topsis_Aniket_102003643.egg-info/requires.txt
Topsis_Aniket_102003643.egg-info/top_level.txt