Metadata-Version: 2.1
Name: Topsis-Aniket-102003643
Version: 0.1
Summary: It is a topsis package.
Home-page: https://github.com/Aniket-Sharma27/Topsis_Aniket_102003643
Author: Aniket Sharma
Author-email: anikets1023@gmail.com
License: MIT
Download-URL: https://github.com/Aniket-Sharma27/Topsis_Aniket_102003643/archive/refs/tags/0.1.tar.gz
Keywords: MCDM,102003643,TOPSIS
Platform: UNKNOWN
Classifier: Development Status :: 3 - Alpha
Classifier: Intended Audience :: Developers
Classifier: Topic :: Software Development :: Build Tools
Classifier: License :: OSI Approved :: MIT License
Classifier: Programming Language :: Python :: 3
Classifier: Programming Language :: Python :: 3.4
Classifier: Programming Language :: Python :: 3.5
Classifier: Programming Language :: Python :: 3.6
